{
  "pref_code": "15",
  "pref_name": "新潟県",
  "investigated_at": "2026-04-23",
  "records": [
    {
      "city_name": "小千谷市",
      "status": "confirmed",
      "sources": [
        {
          "kind": "prefecture_term_expiry_list",
          "title": "新潟県 任期満了日一覧",
          "url": "https://www.pref.niigata.lg.jp/site/senkan/"
        }
      ]
    },
    {
      "city_name": "新潟市",
      "status": "confirmed",
      "sources": [
        {
          "kind": "prefecture_term_expiry_list",
          "title": "新潟県 任期満了日一覧",
          "url": "https://www.pref.niigata.lg.jp/site/senkan/"
        }
      ]
    },
    {
      "city_name": "長岡市",
      "status": "confirmed",
      "sources": [
        {
          "kind": "prefecture_term_expiry_list",
          "title": "新潟県 任期満了日一覧",
          "url": "https://www.pref.niigata.lg.jp/site/senkan/"
        },
        {
          "kind": "municipal_official_page",
          "title": "公式ページ",
          "url": "https://www.pref.niigata.lg.jp/site/senkyo/1198018603173.html",
          "checked_at": "2026-04-21",
          "used_for": [
            "mayor_name",
            "term_start",
            "term_end",
            "term_note"
          ]
        }
      ]
    },
    {
      "city_name": "三条市",
      "status": "confirmed",
      "sources": [
        {
          "kind": "prefecture_term_expiry_list",
          "title": "新潟県 任期満了日一覧",
          "url": "https://www.pref.niigata.lg.jp/site/senkan/"
        },
        {
          "kind": "municipal_official_page",
          "title": "公式ページ",
          "url": "https://www.pref.niigata.lg.jp/site/senkyo/1198018603173.html",
          "checked_at": "2026-04-21",
          "used_for": [
            "mayor_name",
            "term_start",
            "term_end",
            "term_note"
          ]
        }
      ]
    },
    {
      "city_name": "柏崎市",
      "status": "confirmed",
      "sources": [
        {
          "kind": "prefecture_term_expiry_list",
          "title": "新潟県 任期満了日一覧",
          "url": "https://www.pref.niigata.lg.jp/site/senkan/"
        },
        {
          "kind": "municipal_official_page",
          "title": "公式ページ",
          "url": "https://www.pref.niigata.lg.jp/site/senkyo/1198018603173.html",
          "checked_at": "2026-04-21",
          "used_for": [
            "mayor_name",
            "term_start",
            "term_end",
            "term_note"
          ]
        }
      ]
    },
    {
      "city_name": "新発田市",
      "status": "confirmed",
      "sources": [
        {
          "kind": "prefecture_term_expiry_list",
          "title": "新潟県 任期満了日一覧",
          "url": "https://www.pref.niigata.lg.jp/site/senkan/"
        },
        {
          "kind": "municipal_official_page",
          "title": "公式ページ",
          "url": "https://www.pref.niigata.lg.jp/site/senkyo/1198018603173.html",
          "checked_at": "2026-04-21",
          "used_for": [
            "mayor_name",
            "term_start",
            "term_end",
            "term_note"
          ]
        }
      ]
    },
    {
      "city_name": "加茂市",
      "status": "confirmed",
      "sources": [
        {
          "kind": "prefecture_term_expiry_list",
          "title": "新潟県 任期満了日一覧",
          "url": "https://www.pref.niigata.lg.jp/site/senkan/"
        },
        {
          "kind": "municipal_official_page",
          "title": "公式ページ",
          "url": "https://www.pref.niigata.lg.jp/site/senkyo/1198018603173.html",
          "checked_at": "2026-04-21",
          "used_for": [
            "mayor_name",
            "term_start",
            "term_end",
            "term_note"
          ]
        }
      ]
    },
    {
      "city_name": "十日町市",
      "status": "confirmed",
      "sources": [
        {
          "kind": "prefecture_term_expiry_list",
          "title": "新潟県 任期満了日一覧",
          "url": "https://www.pref.niigata.lg.jp/site/senkan/"
        },
        {
          "kind": "municipal_official_page",
          "title": "公式ページ",
          "url": "https://www.pref.niigata.lg.jp/site/senkyo/1198018603173.html",
          "checked_at": "2026-04-21",
          "used_for": [
            "mayor_name",
            "term_start",
            "term_end",
            "term_note"
          ]
        }
      ]
    },
    {
      "city_name": "見附市",
      "status": "confirmed",
      "sources": [
        {
          "kind": "prefecture_term_expiry_list",
          "title": "新潟県 任期満了日一覧",
          "url": "https://www.pref.niigata.lg.jp/site/senkan/"
        },
        {
          "kind": "municipal_official_page",
          "title": "公式ページ",
          "url": "https://www.pref.niigata.lg.jp/site/senkyo/1198018603173.html",
          "checked_at": "2026-04-21",
          "used_for": [
            "mayor_name",
            "term_start",
            "term_end",
            "term_note"
          ]
        }
      ]
    },
    {
      "city_name": "村上市",
      "status": "confirmed",
      "sources": [
        {
          "kind": "prefecture_term_expiry_list",
          "title": "新潟県 任期満了日一覧",
          "url": "https://www.pref.niigata.lg.jp/site/senkan/"
        },
        {
          "kind": "municipal_official_page",
          "title": "公式ページ",
          "url": "https://www.pref.niigata.lg.jp/site/senkyo/1198018603173.html",
          "checked_at": "2026-04-21",
          "used_for": [
            "mayor_name",
            "term_start",
            "term_end",
            "term_note"
          ]
        }
      ]
    },
    {
      "city_name": "燕市",
      "status": "confirmed",
      "sources": [
        {
          "kind": "prefecture_term_expiry_list",
          "title": "新潟県 任期満了日一覧",
          "url": "https://www.pref.niigata.lg.jp/site/senkan/"
        },
        {
          "kind": "municipal_official_page",
          "title": "公式ページ",
          "url": "https://www.pref.niigata.lg.jp/site/senkyo/1198018603173.html",
          "checked_at": "2026-04-21",
          "used_for": [
            "mayor_name",
            "term_start",
            "term_end",
            "term_note"
          ]
        }
      ]
    },
    {
      "city_name": "糸魚川市",
      "status": "confirmed",
      "sources": [
        {
          "kind": "prefecture_term_expiry_list",
          "title": "新潟県 任期満了日一覧",
          "url": "https://www.pref.niigata.lg.jp/site/senkan/"
        },
        {
          "kind": "municipal_official_page",
          "title": "公式ページ",
          "url": "https://www.pref.niigata.lg.jp/site/senkyo/1198018603173.html",
          "checked_at": "2026-04-21",
          "used_for": [
            "mayor_name",
            "term_start",
            "term_end",
            "term_note"
          ]
        }
      ]
    },
    {
      "city_name": "妙高市",
      "status": "confirmed",
      "sources": [
        {
          "kind": "prefecture_term_expiry_list",
          "title": "新潟県 任期満了日一覧",
          "url": "https://www.pref.niigata.lg.jp/site/senkan/"
        },
        {
          "kind": "municipal_official_page",
          "title": "公式ページ",
          "url": "https://www.pref.niigata.lg.jp/site/senkyo/1198018603173.html",
          "checked_at": "2026-04-21",
          "used_for": [
            "mayor_name",
            "term_start",
            "term_end",
            "term_note"
          ]
        }
      ]
    },
    {
      "city_name": "五泉市",
      "status": "confirmed",
      "sources": [
        {
          "kind": "prefecture_term_expiry_list",
          "title": "新潟県 任期満了日一覧",
          "url": "https://www.pref.niigata.lg.jp/site/senkan/"
        },
        {
          "kind": "municipal_official_page",
          "title": "公式ページ",
          "url": "https://www.pref.niigata.lg.jp/site/senkyo/1198018603173.html",
          "checked_at": "2026-04-21",
          "used_for": [
            "mayor_name",
            "term_start",
            "term_end",
            "term_note"
          ]
        }
      ]
    },
    {
      "city_name": "上越市",
      "status": "confirmed",
      "sources": [
        {
          "kind": "prefecture_term_expiry_list",
          "title": "新潟県 任期満了日一覧",
          "url": "https://www.pref.niigata.lg.jp/site/senkan/"
        },
        {
          "kind": "municipal_official_page",
          "title": "公式ページ",
          "url": "https://www.pref.niigata.lg.jp/site/senkyo/1198018603173.html",
          "checked_at": "2026-04-21",
          "used_for": [
            "mayor_name",
            "term_start",
            "term_end",
            "term_note"
          ]
        }
      ]
    },
    {
      "city_name": "阿賀野市",
      "status": "confirmed",
      "sources": [
        {
          "kind": "prefecture_term_expiry_list",
          "title": "新潟県 任期満了日一覧",
          "url": "https://www.pref.niigata.lg.jp/site/senkan/"
        },
        {
          "kind": "municipal_official_page",
          "title": "公式ページ",
          "url": "https://www.pref.niigata.lg.jp/site/senkyo/1198018603173.html",
          "checked_at": "2026-04-21",
          "used_for": [
            "mayor_name",
            "term_start",
            "term_end",
            "term_note"
          ]
        }
      ]
    },
    {
      "city_name": "佐渡市",
      "status": "confirmed",
      "sources": [
        {
          "kind": "prefecture_term_expiry_list",
          "title": "新潟県 任期満了日一覧",
          "url": "https://www.pref.niigata.lg.jp/site/senkan/"
        },
        {
          "kind": "municipal_official_page",
          "title": "公式ページ",
          "url": "https://www.pref.niigata.lg.jp/site/senkyo/1198018603173.html",
          "checked_at": "2026-04-21",
          "used_for": [
            "mayor_name",
            "term_start",
            "term_end",
            "term_note"
          ]
        }
      ]
    },
    {
      "city_name": "魚沼市",
      "status": "confirmed",
      "sources": [
        {
          "kind": "prefecture_term_expiry_list",
          "title": "新潟県 任期満了日一覧",
          "url": "https://www.pref.niigata.lg.jp/site/senkan/"
        },
        {
          "kind": "municipal_official_page",
          "title": "公式ページ",
          "url": "https://www.pref.niigata.lg.jp/site/senkyo/1198018603173.html",
          "checked_at": "2026-04-21",
          "used_for": [
            "mayor_name",
            "term_start",
            "term_end",
            "term_note"
          ]
        }
      ]
    },
    {
      "city_name": "南魚沼市",
      "status": "confirmed",
      "sources": [
        {
          "kind": "prefecture_term_expiry_list",
          "title": "新潟県 任期満了日一覧",
          "url": "https://www.pref.niigata.lg.jp/site/senkan/"
        },
        {
          "kind": "municipal_official_page",
          "title": "公式ページ",
          "url": "https://www.pref.niigata.lg.jp/site/senkyo/1198018603173.html",
          "checked_at": "2026-04-21",
          "used_for": [
            "mayor_name",
            "term_start",
            "term_end",
            "term_note"
          ]
        }
      ]
    },
    {
      "city_name": "胎内市",
      "status": "confirmed",
      "sources": [
        {
          "kind": "prefecture_term_expiry_list",
          "title": "新潟県 任期満了日一覧",
          "url": "https://www.pref.niigata.lg.jp/site/senkan/"
        },
        {
          "kind": "municipal_official_page",
          "title": "公式ページ",
          "url": "https://www.pref.niigata.lg.jp/site/senkyo/1198018603173.html",
          "checked_at": "2026-04-21",
          "used_for": [
            "mayor_name",
            "term_start",
            "term_end",
            "term_note"
          ]
        }
      ]
    }
  ]
}
